{
  "geographical_translations": {
    "regions": {
      "Chicago Loop": "Чиказький Луп",
      "New York City": "Нью-Йорк",
      "Persian Empire Core": "Ядро Перської Імперії",
      "Extended Persian Territories": "Розширені перські території",
      "Ancient Egypt": "Стародавній Єгипет",
      "Lower Egypt": "Нижній Єгипет",
      "Upper Egypt": "Верхній Єгипет",
      "Western Europe": "Західна Європа",
      "Central Europe": "Центральна Європа",
      "Eastern Europe": "Східна Європа",
      "British Isles": "Британські острови",
      "France": "Франція",
      "Germany": "Німеччина",
      "Spain": "Іспанія",
      "Italy": "Італія",
      "Greece": "Греція",
      "Byzantine Empire": "Візантійська Імперія",
      "United States": "Сполучені Штати",
      "Colonial America": "Колоніальна Америка",
      "Russian Empire": "Російська Імперія",
      "Brussels": "Брюссель",
      "Barcelona": "Барселона",
      "Paris": "Париж",
      "New York": "Нью-Йорк",
      "England": "Англія",
      "California": "Каліфорнія",
      "Midwestern United States": "Середньо-західні США",
      "Global Movement": "Глобальний рух",
      "Chicago": "Чикаго",
      "Miami Beach": "Маямі-Біч"
    },
    "descriptions": {
      "Origin of skyscraper architecture": "Походження архітектури хмарочосів",
      "Later development": "Пізніший розвиток",
      "Ancient Persia (modern Iran)": "Стародавня Персія (сучасний Іран)",
      "Greater Persian Empire including Mesopotamia": "Велика Перська Імперія включно з Месопотамією",
      "Heart of ancient Egyptian civilization": "Серце стародавньої єгипетської цивілізації",
      "Capital region of ancient Egypt": "Столичний регіон стародавнього Єгипту",
      "Southern regions with major temples": "Південні регіони з великими храмами",
      "Center of medieval European culture": "Центр середньовічної європейської культури",
      "Birthplace of Gothic architecture": "Батьківщина готичної архітектури",
      "Renaissance architectural innovation": "Ренесансні архітектурні інновації",
      "Victorian architectural development": "Розвиток вікторіанської архітектури",
      "Colonial settlement regions": "Регіони колоніальних поселень",
      "Imperial Russian territories": "Території Російської Імперії"
    },
    "buildings": {
      "Home Insurance Building": "Будівля страхової компанії Хоум",
      "Auditorium Building": "Будівля Аудиторіум",
      "Monadnock Building": "Будівля Монаднок",
      "Reliance Building": "Будівля Релайенс",
      "Carson Pirie Scott Building": "Будівля Карсон Пірі Скотт",
      "Rookery Building": "Будівля Рукері",
      "Persepolis": "Персеполь",
      "Pasargadae": "Пасаргади",
      "Susa Palace": "Палац у Сузах",
      "Naqsh-e Rostam": "Накш-е Рустам",
      "Taq Kasra": "Так Касра",
      "Great Pyramid of Giza": "Велика піраміда Гізи",
      "Temple of Karnak": "Храм Карнак",
      "Abu Simbel": "Абу Сімбел",
      "Temple of Luxor": "Храм Луксор",
      "Pyramid of Djoser": "Піраміда Джосера",
      "Notre-Dame de Paris": "Нотр-Дам де Парі",
      "Chartres Cathedral": "Шартрський собор",
      "Canterbury Cathedral": "Кентерберійський собор",
      "Cologne Cathedral": "Кельнський собор",
      "Westminster Abbey": "Вестмінстерське абатство",
      "Hagia Sophia": "Свята Софія",
      "St. Mark's Basilica": "Базиліка Святого Марка",
      "Ravenna Mosaics": "Равеннські мозаїки",
      "Daphni Monastery": "Монастир Дафні",
      "Casa Batlló": "Каса Батльо",
      "Victor Horta House": "Будинок Віктора Орта",
      "Bauhaus Dessau": "Баухаус Дессау",
      "Fagus Factory": "Фабрика Фагус",
      "Grand Central Terminal": "Центральний вокзал",
      "Opéra Garnier": "Опера Гарньє",
      "St. Marks Basilica": "Базиліка Святого Марка",
      "Independence Hall": "Зал Незалежності",
      "Williamsburg Governors Palace": "Палац губернатора Вільямсбурга",
      "Guggenheim Museum Bilbao": "Музей Гуггенхайма в Більбао",
      "Walt Disney Concert Hall": "Концертний зал Волта Діснея",
      "Jewish Museum Berlin": "Єврейський музей Берліна",
      "Vitra Design Museum": "Музей дизайну Вітра",
      "Dancing House": "Танцювальний будинок",
      "Imperial War Museum North": "Північний музей Імперської війни",
      "One World Trade Center": "Всесвітній торговий центр",
      "Denver Art Museum": "Художній музей Денвера",
      "Parc de la Villette": "Парк де ла Вілетт",
      "Victoria and Albert Museum": "Музей Вікторії та Альберта",
      "Bath Royal Crescent": "Королівський півмісяць у Баті",
      "Parthenon": "Парфенон",
      "US Capitol": "Капітолій США",
      "Seagram Building": "Будівля Сіграм",
      "Villa Savoye": "Вілла Савой",
      "Bauhaus Dessau": "Баухаус Дессау",
      "Tugendhat House": "Будинок Тугендгат",
      "Lovell Health House": "Будинок здоров'я Ловелла",
      "UN Headquarters": "Штаб-квартира ООН",
      "Barcelona Pavilion": "Барселонський павільйон",
      "Lever House": "Будівля Левер Хаус",
      "Lucy the Elephant": "Слон Люсі",
      "Villa Rotonda": "Вілла Ротонда",
      "AT&T Building": "Будівля AT&T",
      "Painted Ladies": "Розмальовані дами",
      "Durham Cathedral": "Даремський собор",
      "St. Basils Cathedral": "Собор Василя Блаженного",
      "Hampton Court Palace": "Палац Хемптон-Корт",
      "Gamble House": "Будинок Гембл",
      "Robie House": "Будинок Робі",
      "Typical Foursquare House": "Типовий чотирикутний будинок",
      "Chrysler Building": "Крайслер Білдінг",
      "Empire State Building": "Емпайр Стейт Білдінг",
      "Radio City Music Hall": "Радіо Сіті Мьюзік Холл",
      "Palace of Versailles": "Версальський палац"
    },
    "building_descriptions": {
      "Chicago - First skyscraper (demolished)": "Чикаго - Перший хмарочос (знесений)",
      "Chicago - Adler & Sullivan": "Чикаго - Адлер і Салліван",
      "Chicago - Tallest masonry building": "Чикаго - Найвища мурована будівля",
      "Chicago - Glass curtain wall pioneer": "Чикаго - Піонер скляних навісних стін",
      "Chicago - Louis Sullivan masterpiece": "Чикаго - Шедевр Луїса Саллівана",
      "Chicago - Burnham & Root design": "Чикаго - Дизайн Бернхема і Рута",
      "Ancient ceremonial capital of the Persian Empire": "Стародавня церемоніальна столиця Перської Імперії",
      "Tomb of Cyrus the Great": "Гробниця Кіра Великого",
      "Winter palace of Persian kings": "Зимовий палац перських царів",
      "Rock tombs of Persian kings": "Скельні гробниці перських царів",
      "Ruins of the great arch at Ctesiphon": "Руїни великої арки в Ктесифоні",
      "Last wonder of the ancient world": "Остання дивина стародавнього світу",
      "Largest ancient temple complex": "Найбільший стародавній храмовий комплекс",
      "Rock-cut temples of Ramesses II": "Висічені в скелі храми Рамзеса II",
      "Major temple complex in ancient Thebes": "Великий храмовий комплекс у стародавніх Фівах",
      "First pyramid with smooth sides": "Перша піраміда з гладкими сторонами",
      "Masterpiece of French Gothic": "Шедевр французької готики",
      "Early Gothic cathedral": "Рання готична катедра",
      "English Gothic architecture": "Англійська готична архітектура",
      "German Gothic cathedral": "Німецька готична катедра",
      "English Gothic abbey": "Англійське готичне абатство",
      "Byzantine architectural marvel": "Візантійське архітектурне диво",
      "Venetian Byzantine architecture": "Венеціанська візантійська архітектура",
      "Byzantine mosaic art": "Візантійське мозаїчне мистецтво",
      "Monastery with Byzantine mosaics": "Монастир з візантійськими мозаїками",
      "Mies van der Rohe's masterpiece": "Шедевр Міса ван дер Рое",
      "Le Corbusier's modernist house": "Модерністський будинок Ле Корбюзьє",
      "Walter Gropius modernist school": "Модерністська школа Вальтера Гропіуса",
      "Mies van der Rohe residence": "Резиденція Міса ван дер Рое",
      "Richard Neutra modernist house": "Модерністський будинок Річарда Нейтри",
      "International modernist complex": "Міжнародний модерністський комплекс",
      "Mies van der Rohe pavilion": "Павільйон Міса ван дер Рое",
      "Skidmore, Owings & Merrill tower": "Вежа Скідмор, Овінгс і Мерілл",
      "Gehry's steel curves": "Сталеві криві Гері",
      "Daniel Libeskind's angular design": "Кутовий дизайн Даніеля Лібескінда",
      "Gehry's white sculptural form": "Біла скульптурна форма Гері",
      "Vlado Milunić and Gehry collaboration": "Співпраця Владо Мілуніча і Гері",
      "Libeskind's fragmented earth": "Фрагментована земля Лібескінда",
      "Libeskind's Freedom Tower design": "Дизайн Вежі Свободи Лібескінда",
      "Libeskind's titanium crystal": "Титановий кристал Лібескінда",
      "Bernard Tschumi's red follies": "Червоні фоллі Бернарда Чумі"
    }
  }
}